gff/__init__.py
python_gff-0.1.3.dist-info/LICENSE
python_gff-0.1.3.dist-info/WHEEL
python_gff-0.1.3.dist-info/METADATA
python_gff-0.1.3.dist-info/RECORD
